bent/__init__.py
bent/annotate.py
bent/get_data.sh
bent/get_kb_dicts.sh
bent/get_kbs.py
bent/requirements.txt
bent/setup_package.py
bent/setup_package.sh
bent/setup_package_wrapper.py
bent/src/__init__.py
bent/src/cfg.py
bent/src/classes.py
bent/src/nel.py
bent/src/ner.py
bent/src/utils.py
bent/src/NILINKER/__init__.py
bent/src/NILINKER/nilinker.py
bent/src/NILINKER/predict_nilinker.py
bent/src/NILINKER/utils.py
bent/src/REEL/__init__.py
bent/src/REEL/candidates.py
bent/src/REEL/information_content.py
bent/src/REEL/post_process.py
bent/src/REEL/ppr_for_ned_all.class
bent/src/REEL/ppr_for_ned_all.java
bent/src/REEL/pre_process.py
bent/src/REEL/run.py
bent/src/REEL/utils.py
bent/src/abbreviation_detector/__init__.py
bent/src/abbreviation_detector/run.py
bent/src/build/__init__.py
bent/src/build/annotations/__init__.py
bent/src/build/annotations/dataset_entities.py
bent/src/build/kb/__init__.py
bent/src/build/kb/generate_dicts.py
bent/src/build/kb/kb.py
bent/src/build/relation_extraction/__init__.py
bent/src/build/relation_extraction/dicts.py
bent/src/dicts/__init__.py
bent/src/dicts/annotations/__init__.py
bent/src/dicts/annotations/dataset_entities.py
bent/src/dicts/kb/__init__.py
bent/src/dicts/kb/generate_dicts.py
bent/src/dicts/kb/kb.py
bent/src/dicts/relation_extraction/__init__.py
bent/src/dicts/relation_extraction/dicts.py
bent-0.0.80.dist-info/LICENSE.txt
bent-0.0.80.dist-info/METADATA
bent-0.0.80.dist-info/WHEEL
bent-0.0.80.dist-info/entry_points.txt
bent-0.0.80.dist-info/top_level.txt
bent-0.0.80.dist-info/RECORD
