Metadata-Version: 2.1
Name: bent
Version: 0.0.80
Summary: BENT: Biomedical Entity Annotator
Home-page: https://github.com/lasigeBioTM/bent
Author: Pedro Ruas
Author-email: pedrosimruas@gmail.com
License: Apache License
Keywords: text mining,natural language processing,entity extraction,named entity recognition,named entity linking,normalization,disambiguation,NER,NEL,information extraction
Classifier: Development Status :: 3 - Alpha
Classifier: Intended Audience :: Developers
Classifier: Intended Audience :: Science/Research
Classifier: Intended Audience :: Information Technology
Classifier: Topic :: Software Development :: Build Tools
Classifier: Topic :: Scientific/Engineering :: Bio-Informatics
Classifier: Topic :: Scientific/Engineering :: Artificial Intelligence
Classifier: Programming Language :: Python :: 3.7
Classifier: Programming Language :: Python :: 3.8
Classifier: Programming Language :: Python :: 3.9
Classifier: Programming Language :: Python
Classifier: Programming Language :: Unix Shell
Classifier: Programming Language :: Java
Classifier: Operating System :: POSIX :: Linux
Classifier: License :: OSI Approved :: Apache Software License
Requires-Python: >=3.7, <=3.10.13
License-File: LICENSE.txt
Requires-Dist: obonet ==0.3.0
Requires-Dist: networkx ==2.5.1
Requires-Dist: gdown ==4.6.0
Requires-Dist: rapidfuzz ==2.0.2
Requires-Dist: tqdm ==4.66
Requires-Dist: seqeval ==1.2.2
Requires-Dist: orjson ==3.8.5
Requires-Dist: psutil
Requires-Dist: tensorflow-gpu ==2.5.1 ; python_version < "3.10"
Requires-Dist: transformers ==4.9.0 ; python_version < "3.10"
Requires-Dist: torch ==1.9.1 ; python_version < "3.10"
Requires-Dist: spacy ==3.0.1 ; python_version < "3.10"
Requires-Dist: tensorflow ==2.13.1 ; python_version == "3.10"
Requires-Dist: transformers ==4.35.2 ; python_version == "3.10"
Requires-Dist: torch ==2.0 ; python_version == "3.10"
Requires-Dist: spacy ==3.7.2 ; python_version == "3.10"
